kantag/__init__.py
kantag/_version.py
kantag/applykan.py
kantag/audiofile.py
kantag/exceptions.py
kantag/initkan.py
kantag/listdict.py
kantag/musicbrainz.py
kantag/showkan.py
kantag/tagfile.py
kantag/tagmaps.py
kantag/tagset.py
kantag/tagstores.py
kantag/textencoding.py
kantag/util.py
kantag-2.0.0.dist-info/LICENSE.txt
kantag-2.0.0.dist-info/METADATA
kantag-2.0.0.dist-info/WHEEL
kantag-2.0.0.dist-info/entry_points.txt
kantag-2.0.0.dist-info/top_level.txt
kantag-2.0.0.dist-info/RECORD
