Metadata-Version: 2.1
Name: kantag
Version: 2.0.0
Summary: Manage audio file metadata using external text files.
Home-page: https://github.com/dgasaway/kantag
Author: David Gasaway
Author-email: dave@gasaway.org
License: GNU GPL v2
Download-URL: https://github.com/dgasaway/kantag/releases
Keywords: audio music metadata tags
Platform: UNKNOWN
Classifier: Operating System :: OS Independent
Classifier: Programming Language :: Python :: 3
Classifier: Programming Language :: Python :: 3.7
Classifier: Programming Language :: Python :: 3 :: Only
Classifier: License :: OSI Approved :: GNU General Public License v2 (GPLv2)
Classifier: Topic :: Multimedia :: Sound/Audio
Classifier: Topic :: Software Development :: Libraries :: Python Modules
Classifier: Development Status :: 5 - Production/Stable
Classifier: Environment :: Console
Classifier: Intended Audience :: Developers
Classifier: Intended Audience :: End Users/Desktop
Requires-Python: ~=3.7
Requires-Dist: mutagen (>=1.40)
Provides-Extra: musicbrainz
Requires-Dist: musicbrainzngs (>=0.6) ; extra == 'musicbrainz'
